cognitive_face/__init__.py
cognitive_face/face.py
cognitive_face/face_list.py
cognitive_face/large_face_list.py
cognitive_face/large_face_list_face.py
cognitive_face/large_person_group.py
cognitive_face/large_person_group_person.py
cognitive_face/large_person_group_person_face.py
cognitive_face/person.py
cognitive_face/person_group.py
cognitive_face/util.py
cognitive_face/tests/__init__.py
cognitive_face/tests/config.sample.py
cognitive_face/tests/test_face.py
cognitive_face/tests/test_face_list.py
cognitive_face/tests/test_large_face_list.py
cognitive_face/tests/test_large_face_list_face.py
cognitive_face/tests/test_large_person_group.py
cognitive_face/tests/test_large_person_group_person.py
cognitive_face/tests/test_large_person_group_person_face.py
cognitive_face/tests/test_person.py
cognitive_face/tests/test_person_group.py
cognitive_face/tests/util.py
cognitive_face-1.5.0.dist-info/LICENSE-IMAGE.md
cognitive_face-1.5.0.dist-info/LICENSE.md
cognitive_face-1.5.0.dist-info/METADATA
cognitive_face-1.5.0.dist-info/WHEEL
cognitive_face-1.5.0.dist-info/top_level.txt
cognitive_face-1.5.0.dist-info/RECORD
