Metadata-Version: 2.1
Name: cognitive-face
Version: 1.5.0
Summary: Python SDK for the Cognitive Face API
Home-page: https://github.com/Microsoft/Cognitive-Face-Python
Author: Microsoft
License: MIT
Platform: UNKNOWN
Classifier: Development Status :: 5 - Production/Stable
Classifier: Intended Audience :: Developers
Classifier: License :: OSI Approved :: MIT License
Classifier: Programming Language :: Python :: 2.7
Classifier: Programming Language :: Python :: 3
Classifier: Topic :: Scientific/Engineering :: Image Recognition
